LICENSE.txt
MANIFEST.in
README.md
awsauth.py
example.py
setup.py
test.py
requests_aws.egg-info/PKG-INFO
requests_aws.egg-info/SOURCES.txt
requests_aws.egg-info/dependency_links.txt
requests_aws.egg-info/requires.txt
requests_aws.egg-info/top_level.txt