Metadata-Version: 1.0
Name: requests-aws
Version: 0.1.5
Summary: AWS authentication for Amazon S3 for the python requests module
Home-page: https://github.com/tax/python-requests-aws
Author: Paul Tax
Author-email: paultax@gmail.com
License: BSD licence, see LICENCE.txt
Platform: UNKNOWN
